mathcad2smath/__init__.py
mathcad2smath/converter.py
mathcad2smath/custom_mathcad_functions.py
mathcad2smath/mathcad2smath.py
mathcad2smath/core/__init__.py
mathcad2smath/core/templates.py
mathcad2smath/core/converters/__init__.py
mathcad2smath/core/converters/ifthen.py
mathcad2smath/core/converters/inline_operations.py
mathcad2smath/core/converters/link.py
mathcad2smath/core/converters/sequence_to_matrix.py
mathcad2smath/core/converters/summation.py
mathcad2smath/core/utils/__init__.py
mathcad2smath/core/utils/utils.py
mathcad2smath-1.8.1.dist-info/LICENSE
mathcad2smath-1.8.1.dist-info/METADATA
mathcad2smath-1.8.1.dist-info/WHEEL
mathcad2smath-1.8.1.dist-info/entry_points.txt
mathcad2smath-1.8.1.dist-info/top_level.txt
mathcad2smath-1.8.1.dist-info/RECORD
